{
  "posted": "2026-07-22",
  "expires": "2026-07-26T23:59:59-04:00",
  "heading": "This Week's Specials",
  "items": [
    {
      "name": "LOBSTER BISQUE 12"
    },
    {
      "name": "ZUCCHINI FRIES W/A SIDE OF MARINARA DIPPING SAUCE 10"
    },
    {
      "name": "MEXICAN STREET CORN 10"
    },
    {
      "name": "STEAK FRITES SLICED STEAK TIPS WITH CHIMICHURI SAUCE OVER"
    },
    {
      "name": "HOUSE MADE FRIES 17"
    },
    {
      "name": "SESAME ENCRUSTED AHI TUNA OVER SEAWEED SALAD 15"
    },
    {
      "name": "CUBAN SANDWICH PORK, HAM, SWISS CHEESE, PICKLES AND MUSTARD SERVED WITH FRIES 15"
    },
    {
      "name": "FRIED SEAFOOD PLATTER COD, CRAB CAKE AND COCONUT SHRIMP SERVED WITH HOUSE MADE FRIES 24"
    },
    {
      "name": "SURF AND TURF CHOICE OF STEAK WITH SHRIMP SERVED WITH POTATO AND VEGGIE 32"
    }
  ]
}
